keystem.py
keystem/__init__.py
keystem/_kmeans.py
keystem/keystem.py
keystem-1.0.5.dist-info/METADATA
keystem-1.0.5.dist-info/WHEEL
keystem-1.0.5.dist-info/entry_points.txt
keystem-1.0.5.dist-info/top_level.txt
keystem-1.0.5.dist-info/RECORD
