Metadata-Version: 2.1
Name: keystem
Version: 1.0.5
Summary: Extract the keywords from the given text and assign root of the key for each cluster keys
Home-page: https://github.com/Nagakiran1/keystem.git
Author: Naga
Author-email: Naga <naga@caspai.in>
Project-URL: Homepage, https://github.com/Nagakiran1/keystem
Keywords: text,keywords,bert,keybert
Classifier: License :: OSI Approved :: MIT License
Classifier: Programming Language :: Python
Classifier: Programming Language :: Python :: 3
Requires-Python: >=3.6.0
Requires-Dist: nltk (>=3.7)
Requires-Dist: keybert (>=0.7.0)
Requires-Dist: spacy (>=3.3.0)
Requires-Dist: pandas (>=1.1.5)
Requires-Dist: numpy (>=1.19.5)
Requires-Dist: tomli ; python_version < "3.11"
Provides-Extra: dev
Requires-Dist: black ; extra == 'dev'
Requires-Dist: bumpver ; extra == 'dev'
Requires-Dist: isort ; extra == 'dev'
Requires-Dist: pip-tools ; extra == 'dev'
Requires-Dist: pytest ; extra == 'dev'
